ironarms/__init__.py
ironarms/cli.py
ironarms/data/__init__.py
ironarms/data/chronicle_item.py
ironarms/data/chronicle_model.py
ironarms/middlewares/__init__.py
ironarms/pipelines/__init__.py
ironarms/pipelines/pg_pipeline.py
ironarms/utils/__init__.py
ironarms/utils/db.py
ironarms/utils/helper.py
ironarms/utils/io.py
ironarms/utils/model.py
ironarms/utils/path.py
ironarms/utils/spider.py
ironarms/utils/url.py
ironarms-0.2.0.dist-info/LICENSE
ironarms-0.2.0.dist-info/METADATA
ironarms-0.2.0.dist-info/WHEEL
ironarms-0.2.0.dist-info/entry_points.txt
ironarms-0.2.0.dist-info/top_level.txt
ironarms-0.2.0.dist-info/RECORD
