Metadata-Version: 2.1
Name: ironarms
Version: 0.2.0
Summary: Awesome ironarms created by oirontro
Home-page: https://github.com/oirontro/ironarms/
Author: oirontro
License: UNKNOWN
Platform: UNKNOWN
License-File: LICENSE
Requires-Dist: fire
Requires-Dist: sqlalchemy
Requires-Dist: scrapy
Requires-Dist: dateparser
Provides-Extra: test
Requires-Dist: pytest ; extra == 'test'
Requires-Dist: coverage ; extra == 'test'
Requires-Dist: flake8 ; extra == 'test'
Requires-Dist: black ; extra == 'test'
Requires-Dist: isort ; extra == 'test'
Requires-Dist: pytest-cov ; extra == 'test'
Requires-Dist: codecov ; extra == 'test'
Requires-Dist: gitchangelog ; extra == 'test'
Requires-Dist: mkdocs ; extra == 'test'
